MANIFEST.in
README.rst
bottle_mongo.py
requirements.txt
setup.py
bottle_mongo.egg-info/PKG-INFO
bottle_mongo.egg-info/SOURCES.txt
bottle_mongo.egg-info/dependency_links.txt
bottle_mongo.egg-info/requires.txt
bottle_mongo.egg-info/top_level.txt