Metadata-Version: 1.1
Name: bottle-mongo
Version: 0.2.4
Summary: MongoDB integration for Bottle
Home-page: https://github.com/bottlepy/bottle-mongo
Author: Thiago Avelino
Author-email: thiago@avelino.xxx
License: MIT
Platform: any
Classifier: Environment :: Web Environment
Classifier: Environment :: Plugins
Classifier: Framework :: Bottle
Classifier: Intended Audience :: Developers
Classifier: License :: OSI Approved :: MIT License
Classifier: Operating System :: OS Independent
Classifier: Programming Language :: Python
Classifier: Topic :: Internet :: WWW/HTTP :: Dynamic Content
Classifier: Topic :: Software Development :: Libraries :: Python Modules
